neps/__init__.py
neps/api.py
neps/env.py
neps/exceptions.py
neps/normalization.py
neps/py.typed
neps/runtime.py
neps/validation.py
neps/optimizers/__init__.py
neps/optimizers/algorithms.py
neps/optimizers/ask_and_tell.py
neps/optimizers/bayesian_optimization.py
neps/optimizers/bracket_optimizer.py
neps/optimizers/grid_search.py
neps/optimizers/ifbo.py
neps/optimizers/mopriors.py
neps/optimizers/neps_bracket_optimizer.py
neps/optimizers/neps_local_and_incumbent.py
neps/optimizers/neps_priorband.py
neps/optimizers/neps_random_search.py
neps/optimizers/neps_regularized_evolution.py
neps/optimizers/optimizer.py
neps/optimizers/primo.py
neps/optimizers/priorband.py
neps/optimizers/random_search.py
neps/optimizers/acquisition/__init__.py
neps/optimizers/acquisition/cost_cooling.py
neps/optimizers/acquisition/pibo.py
neps/optimizers/acquisition/weighted_acquisition.py
neps/optimizers/models/__init__.py
neps/optimizers/models/ftpfn.py
neps/optimizers/models/gp.py
neps/optimizers/utils/__init__.py
neps/optimizers/utils/brackets.py
neps/optimizers/utils/grid.py
neps/optimizers/utils/initial_design.py
neps/optimizers/utils/util.py
neps/optimizers/utils/multiobjective/__init__.py
neps/optimizers/utils/multiobjective/epsnet.py
neps/plot/__init__.py
neps/plot/__main__.py
neps/plot/plot.py
neps/plot/plot3D.py
neps/plot/plotting.py
neps/plot/read_results.py
neps/plot/tensorboard_eval.py
neps/sampling/__init__.py
neps/sampling/distributions.py
neps/sampling/priors.py
neps/sampling/samplers.py
neps/space/__init__.py
neps/space/domain.py
neps/space/encoding.py
neps/space/parameters.py
neps/space/parsing.py
neps/space/search_space.py
neps/space/neps_spaces/__init__.py
neps/space/neps_spaces/neps_space.py
neps/space/neps_spaces/parameters.py
neps/space/neps_spaces/sampling.py
neps/space/neps_spaces/string_formatter.py
neps/state/__init__.py
neps/state/err_dump.py
neps/state/filebased.py
neps/state/neps_state.py
neps/state/optimizer.py
neps/state/pipeline_eval.py
neural_pipeline_search-0.15.0.dist-info/licenses/LICENSE
neural_pipeline_search-0.15.0.dist-info/METADATA
neural_pipeline_search-0.15.0.dist-info/WHEEL
neural_pipeline_search-0.15.0.dist-info/top_level.txt
neural_pipeline_search-0.15.0.dist-info/RECORD
