Metadata-Version: 2.4
Name: neural-pipeline-search
Version: 0.15.0
Summary: Neural Pipeline Search helps deep learning experts find the best neural pipeline.
Author: Eddie Bergman, Simon Schrodi, Soham Basu, Anton Merlin Geburek, Tarek Abou Chakra, Samir Garibov, Gopalji Gaur, Maciej Janowski, Carl Hvarfner, Timur Carstensen, Ema Mekic, Daniel Rogalla, Binxin Ru, Frank Hutter
Author-email: Danny Stoll <stolld@cs.uni-freiburg.de>, Neeratyoy Mallik <mallik@cs.uni-freiburg.de>, Nastaran Alipour <mallik@cs.uni-freiburg.de>
License: 
Project-URL: homepage, https://github.com/automl/neps
Project-URL: repository, https://github.com/automl/neps
Project-URL: documentation, https://automl.github.io/neps/
Keywords: Deep Learning,Neural Pipeline Search,Neural Architecture Search,Hyperparameter Optimization,AutoML
Classifier: Development Status :: 4 - Beta
Classifier: Intended Audience :: Developers
Classifier: Intended Audience :: Science/Research
Classifier: Natural Language :: English
Classifier: License :: OSI Approved :: Apache Software License
Classifier: Operating System :: POSIX :: Linux
Classifier: Operating System :: Microsoft :: Windows
Classifier: Operating System :: MacOS
Classifier: Programming Language :: Python :: 3.10
Classifier: Programming Language :: Python :: 3.11
Classifier: Programming Language :: Python :: 3.12
Classifier: Programming Language :: Python :: 3.13
Classifier: Topic :: Scientific/Engineering :: Artificial Intelligence
Classifier: Topic :: System :: Distributed Computing
Requires-Python: <3.14,>=3.10
License-File: LICENSE
Requires-Dist: numpy>=2.0
Requires-Dist: pandas<3.0,>=2.0
Requires-Dist: networkx<3.0,>=2.6.3
Requires-Dist: scipy>=1.13.1
Requires-Dist: torch>=2.0.1
Requires-Dist: matplotlib<4.0,>=3.0
Requires-Dist: more-itertools
Requires-Dist: portalocker<3.0,>=2.0
Requires-Dist: seaborn<0.14,>=0.13
Requires-Dist: pyyaml<7.0,>=6.0
Requires-Dist: tensorboard<3.0,>=2.0
Requires-Dist: typing-extensions
Requires-Dist: torchvision>=0.8.0
Requires-Dist: botorch>=0.12
Requires-Dist: gpytorch==1.13.0
Requires-Dist: ifbo>=0.3.13
Provides-Extra: dev
Requires-Dist: ruff; extra == "dev"
Requires-Dist: pre-commit<4,>=3; extra == "dev"
Requires-Dist: mypy<2,>=1; extra == "dev"
Requires-Dist: pytest<8,>=7; extra == "dev"
Requires-Dist: pytest-cases<4,>=3; extra == "dev"
Requires-Dist: pytest-repeat<1,>=0; extra == "dev"
Requires-Dist: types-PyYAML<7,>=6; extra == "dev"
Requires-Dist: mkdocs-material; extra == "dev"
Requires-Dist: mkdocs-autorefs; extra == "dev"
Requires-Dist: mkdocs-gen-files; extra == "dev"
Requires-Dist: mkdocstrings[python]; extra == "dev"
Requires-Dist: mkdocs-literate-nav; extra == "dev"
Requires-Dist: pymdown-extensions; extra == "dev"
Requires-Dist: mike; extra == "dev"
Requires-Dist: black; extra == "dev"
Dynamic: license-file
